Metadata-Version: 1.0
Name: openiot
Version: 0.3.1.4
Summary: OpenIoT Gateway
Home-page: http://www.openiot.org.ng
Author: Ahmad Sadiq
Author-email: sadiq.a.ahmad@gmail.com
License: BSD
Platform: UNKNOWN
